AUTHORS
LICENSE
README.md
pyproject.toml
birdeye_py.egg-info/PKG-INFO
birdeye_py.egg-info/SOURCES.txt
birdeye_py.egg-info/dependency_links.txt
birdeye_py.egg-info/requires.txt
birdeye_py.egg-info/top_level.txt
birdeyepy/__init__.py
birdeyepy/birdeye.py
birdeyepy/py.typed
birdeyepy/resources/__init__.py
birdeyepy/resources/defi.py
birdeyepy/resources/pair.py
birdeyepy/resources/search.py
birdeyepy/resources/token.py
birdeyepy/resources/trader.py
birdeyepy/resources/wallet.py
birdeyepy/utils/__init__.py
birdeyepy/utils/constants.py
birdeyepy/utils/enums.py
birdeyepy/utils/exceptions.py
birdeyepy/utils/helpers.py
birdeyepy/utils/http.py
birdeyepy/utils/interfaces.py
birdeyepy/utils/types.py