Metadata-Version: 2.1
Name: birdeye-py
Version: 0.0.9
Summary: Python wrapper for birdeye.so api
Maintainer-email: Nick Kelly <nialexanderke@proton.me>
Project-URL: Homepage, https://github.com/nickatnight/birdeye-py
Project-URL: Issues, https://github.com/nickatnight/birdeye-py/issues
Classifier: Development Status :: 4 - Beta
Classifier: Intended Audience :: Developers
Classifier: License :: OSI Approved :: MIT License
Classifier: Programming Language :: Python :: 3
Classifier: Programming Language :: Python :: 3.9
Classifier: Programming Language :: Python :: 3.10
Classifier: Programming Language :: Python :: 3.11
Classifier: Programming Language :: Python :: 3.12
Classifier: Programming Language :: Python :: 3.13
Classifier: Topic :: Software Development :: Libraries :: Python Modules
Classifier: Typing :: Typed
Requires-Python: >=3.9
License-File: LICENSE
License-File: AUTHORS
Requires-Dist: requests==2.32.3
